examples/add_to_google_sheet.py
examples/native_memory.py
examples/web_scraping.py
mayalabs/__init__.py
mayalabs/cli.py
mayalabs/exceptions.py
mayalabs/function.py
mayalabs/mayalabs.py
mayalabs/session.py
mayalabs/worker.py
mayalabs/utils/__init__.py
mayalabs/utils/defaults.py
mayalabs/utils/general.py
mayalabs/utils/log.py
mayalabs/utils/logging.py
mayalabs/utils/name_gen.py
mayalabs/utils/pac_engine.py
mayalabs/utils/poll.py
mayalabs/utils/websocket.py
tests/__init__.py
tests/example_1.py
tests/example_2.py
tests/example_3.py
usage/function.py
usage/sql_test.py
mayalabs-0.0.9.dist-info/LICENCE
mayalabs-0.0.9.dist-info/METADATA
mayalabs-0.0.9.dist-info/WHEEL
mayalabs-0.0.9.dist-info/entry_points.txt
mayalabs-0.0.9.dist-info/top_level.txt
mayalabs-0.0.9.dist-info/RECORD
