Metadata-Version: 2.1
Name: mayalabs
Version: 0.0.9
Summary: Python SDK for Maya Labs' natural language programming paradigm
Author-email: Maya Support <humans@mayalabs.io>
Maintainer-email: Maya Support <humans@mayalabs.io>
Project-URL: homepage, https://mayalabs.io
Project-URL: repository, https://github.com/mayahq/mayalabs-sdk-python
Requires-Python: >=3.6
License-File: LICENCE
Requires-Dist: requests
Requires-Dist: pydantic
Requires-Dist: websockets
Requires-Dist: click
Requires-Dist: colorama
Requires-Dist: halo
Requires-Dist: simple-term-menu
Requires-Dist: aiohttp (<4.0,>=3.6)
Provides-Extra: test
Requires-Dist: pytest (==7.2.1) ; extra == 'test'
